transcat/__init__.py
transcat/__main__.py
transcat/calculation.py
transcat-0.1.0.dist-info/METADATA
transcat-0.1.0.dist-info/WHEEL
transcat-0.1.0.dist-info/top_level.txt
transcat-0.1.0.dist-info/RECORD
